[
    {
        "productName": "Silver Shovel",
        "image": "https://i5.walmartimages.com/asr/304c33ee-f659-4097-b430-ab9fcc906980.5e6fbf38625a1e543f58bf09f16eacae.jpeg?odnHeight=612&odnWidth=612&odnBg=FFFFFF",
        "description": "Best Shovel on the planet. We made geniune products. Most affordable shovel in the city.",
        "minimumOrderQuantity": 100,
        "availableQuantity": 30000,
        "perUnitPrice": 250
    },
    {
        "productName": "Silver Shovel",
        "image": "https://i5.walmartimages.com/asr/304c33ee-f659-4097-b430-ab9fcc906980.5e6fbf38625a1e543f58bf09f16eacae.jpeg?odnHeight=612&odnWidth=612&odnBg=FFFFFF",
        "description": "Best Shovel on the planet. We made geniune products. Most affordable shovel in the city.",
        "minimumOrderQuantity": 100,
        "availableQuantity": 30000,
        "perUnitPrice": 250
    },
    {
        "productName": "Silver Shovel",
        "image": "https://i5.walmartimages.com/asr/304c33ee-f659-4097-b430-ab9fcc906980.5e6fbf38625a1e543f58bf09f16eacae.jpeg?odnHeight=612&odnWidth=612&odnBg=FFFFFF",
        "description": "Best Shovel on the planet. We made geniune products. Most affordable shovel in the city.",
        "minimumOrderQuantity": 100,
        "availableQuantity": 30000,
        "perUnitPrice": 250
    },
    {
        "productName": "Silver Shovel",
        "image": "https://i5.walmartimages.com/asr/304c33ee-f659-4097-b430-ab9fcc906980.5e6fbf38625a1e543f58bf09f16eacae.jpeg?odnHeight=612&odnWidth=612&odnBg=FFFFFF",
        "description": "Best Shovel on the planet. We made geniune products. Most affordable shovel in the city.",
        "minimumOrderQuantity": 100,
        "availableQuantity": 30000,
        "perUnitPrice": 250
    },
    {
        "productName": "Silver Shovel",
        "image": "https://i5.walmartimages.com/asr/304c33ee-f659-4097-b430-ab9fcc906980.5e6fbf38625a1e543f58bf09f16eacae.jpeg?odnHeight=612&odnWidth=612&odnBg=FFFFFF",
        "description": "Best Shovel on the planet. We made geniune products. Most affordable shovel in the city.",
        "minimumOrderQuantity": 100,
        "availableQuantity": 30000,
        "perUnitPrice": 250
    },
    {
        "productName": "Silver Shovel",
        "image": "https://i5.walmartimages.com/asr/304c33ee-f659-4097-b430-ab9fcc906980.5e6fbf38625a1e543f58bf09f16eacae.jpeg?odnHeight=612&odnWidth=612&odnBg=FFFFFF",
        "description": "Best Shovel on the planet. We made geniune products. Most affordable shovel in the city.",
        "minimumOrderQuantity": 100,
        "availableQuantity": 30000,
        "perUnitPrice": 250
    },
    {
        "productName": "Silver Shovel",
        "image": "https://i5.walmartimages.com/asr/304c33ee-f659-4097-b430-ab9fcc906980.5e6fbf38625a1e543f58bf09f16eacae.jpeg?odnHeight=612&odnWidth=612&odnBg=FFFFFF",
        "description": "Best Shovel on the planet. We made geniune products. Most affordable shovel in the city.",
        "minimumOrderQuantity": 100,
        "availableQuantity": 30000,
        "perUnitPrice": 250
    }
]